primellm/__init__.py
primellm/async_client.py
primellm/cli.py
primellm/client.py
primellm/errors.py
primellm/streaming.py
primellm/structured.py
primellm/tokenizer.py
primellm/tools.py
primellm-1.0.1.dist-info/METADATA
primellm-1.0.1.dist-info/WHEEL
primellm-1.0.1.dist-info/entry_points.txt
primellm-1.0.1.dist-info/top_level.txt
primellm-1.0.1.dist-info/RECORD
