Metadata-Version: 2.4
Name: primellm
Version: 1.0.1
Summary: Official Python SDK for PrimeLLM - Tool calling, streaming, multi-turn agents
Author-email: PrimeLLM <support@primellm.in>
License: MIT
Project-URL: Homepage, https://primellm.in
Project-URL: Documentation, https://primellm.in/docs
Project-URL: Repository, https://github.com/primellm/primellm-python
Keywords: ai,llm,sdk,primellm,gpt,claude,gemini,openai,streaming
Classifier: Development Status :: 4 - Beta
Classifier: Intended Audience :: Developers
Classifier: License :: OSI Approved :: MIT License
Classifier: Operating System :: OS Independent
Classifier: Programming Language :: Python :: 3
Classifier: Programming Language :: Python :: 3.10
Classifier: Programming Language :: Python :: 3.11
Classifier: Programming Language :: Python :: 3.12
Classifier: Topic :: Scientific/Engineering :: Artificial Intelligence
Requires-Python: >=3.10
Requires-Dist: httpx>=0.27.0
Provides-Extra: pydantic
Requires-Dist: pydantic>=2.0; extra == "pydantic"
Provides-Extra: all
Requires-Dist: pydantic>=2.0; extra == "all"
